[
  {
    "obj_attr": "None",
    "obj_id": "1",
    "obj_type": "Van",
    "psr": {
      "position": {
        "x": -12.4458093907425,
        "y": -14.370954427881694,
        "z": -4.033549914639142
      },
      "rotation": {
        "x": -0.0006854674079514373,
        "y": 0.02617096551965529,
        "z": -3.115412714809878
      },
      "scale": {
        "x": 5.001573763767762,
        "y": 1.648538155724641,
        "z": 1.5498094213600053
      }
    }
  },
  {
    "obj_attr": "None",
    "obj_id": "2",
    "obj_type": "Light_Car",
    "psr": {
      "position": {
        "x": -32.38216763992311,
        "y": -9.870818168388983,
        "z": -2.717305513713337
      },
      "rotation": {
        "x": 0.18835091919114846,
        "y": 0.034357199059500014,
        "z": 2.7924442168028376
      },
      "scale": {
        "x": 2.6467060840544696,
        "y": 1.2529776454694774,
        "z": 0.7306206988584759
      }
    }
  },
  {
    "obj_attr": "None",
    "obj_id": "3",
    "obj_type": "Car",
    "psr": {
      "position": {
        "x": 4.008424183602682,
        "y": -21.684444780627253,
        "z": -3.6652314420176575
      },
      "rotation": {
        "x": -0.05305066261555073,
        "y": 0.0018088095800414606,
        "z": -3.0106929596902186
      },
      "scale": {
        "x": 4.3738010630575,
        "y": 1.6619450859009357,
        "z": 1.3751369171541594
      }
    }
  },
  {
    "obj_attr": "None",
    "obj_id": "4",
    "obj_type": "SUV",
    "psr": {
      "position": {
        "x": -6.287251723445742,
        "y": -23.52124231127866,
        "z": -3.5703936154917826
      },
      "rotation": {
        "x": -0.0407903918547071,
        "y": -0.038190419527396574,
        "z": -3.0630528372500483
      },
      "scale": {
        "x": 4.023132898539558,
        "y": 1.4974291891571525,
        "z": 1.6585424643438689
      }
    }
  },
  {
    "obj_attr": "None",
    "obj_id": "5",
    "obj_type": "Van",
    "psr": {
      "position": {
        "x": -16.74180213409235,
        "y": -17.224427346018956,
        "z": -4.033671256790411
      },
      "rotation": {
        "x": -0.00022844276307449295,
        "y": 0.00872365578037716,
        "z": -3.115412714809878
      },
      "scale": {
        "x": 4.78399150542657,
        "y": 1.7049560502375805,
        "z": 1.6469282029643444
      }
    }
  },
  {
    "obj_attr": "None",
    "obj_id": "6",
    "obj_type": "Car",
    "psr": {
      "position": {
        "x": -13.725703586949429,
        "y": -24.151060892511325,
        "z": -4.223051889640583
      },
      "rotation": {
        "x": -0.05104546007256521,
        "y": -0.05364203945276305,
        "z": -3.0630528372500483
      },
      "scale": {
        "x": 4.682926655224358,
        "y": 1.4397245037126463,
        "z": 0.9768147320362501
      }
    }
  },
  {
    "obj_attr": "None",
    "obj_id": "7",
    "obj_type": "Van",
    "psr": {
      "position": {
        "x": -15.481681720847332,
        "y": -27.7956133729017,
        "z": -4.013599687523299
      },
      "rotation": {
        "x": -0.03400338805140377,
        "y": -0.061014486292433195,
        "z": -3.0031206305437377
      },
      "scale": {
        "x": 4.478149102962829,
        "y": 1.8949941779024884,
        "z": 1.4440721643526295
      }
    }
  },
  {
    "obj_attr": "None",
    "obj_id": "8",
    "obj_type": "Light_Car",
    "psr": {
      "position": {
        "x": -8.807958051957552,
        "y": -29.950065651492373,
        "z": -3.467781694393534
      },
      "rotation": {
        "x": -0.038733381845301416,
        "y": -0.056080064729663266,
        "z": -3.052382782511128
      },
      "scale": {
        "x": 3.2780672831114464,
        "y": 1.2994031920942974,
        "z": 1.3695489642037741
      }
    }
  },
  {
    "obj_attr": "None",
    "obj_id": "10",
    "obj_type": "Car",
    "psr": {
      "position": {
        "x": 1.6387026500733095,
        "y": -11.807222934641867,
        "z": -4.357731199259984
      },
      "rotation": {
        "x": -0.08564679686880468,
        "y": -0.024205767105912955,
        "z": -3.0106929596902186
      },
      "scale": {
        "x": 4.862619784718758,
        "y": 1.8309357453394348,
        "z": 1.4748398594112704
      }
    }
  },
  {
    "obj_attr": "None",
    "obj_id": "11",
    "obj_type": "SUV",
    "psr": {
      "position": {
        "x": 13.679559881225254,
        "y": -21.207931056042078,
        "z": -3.8870341384863734
      },
      "rotation": {
        "x": -0.05646367235692944,
        "y": 0.027777446955724858,
        "z": -3.0106929596902186
      },
      "scale": {
        "x": 4.380755643039305,
        "y": 1.5613102359201414,
        "z": 1.3689440622182354
      }
    }
  },
  {
    "obj_attr": "None",
    "obj_id": "12",
    "obj_type": "Small_Truck",
    "psr": {
      "position": {
        "x": 6.970152179318904,
        "y": -25.221298277962543,
        "z": -2.951190403084137
      },
      "rotation": {
        "x": -0.03917911492639085,
        "y": 0.030023968874278356,
        "z": -3.0091907042004795
      },
      "scale": {
        "x": 5.237730225434811,
        "y": 1.5982336207995163,
        "z": 2.5474490811662567
      }
    }
  },
  {
    "obj_attr": "None",
    "obj_id": "13",
    "obj_type": "Two_Wheeler",
    "psr": {
      "position": {
        "x": 11.127772417687584,
        "y": -16.77097887242995,
        "z": -3.9784273879743814
      },
      "rotation": {
        "x": -0.026155682054723225,
        "y": -0.0005547201067855894,
        "z": -3.117548586164173
      },
      "scale": {
        "x": 1.9080718980487035,
        "y": 0.6400892420018315,
        "z": 1.2524295282209936
      }
    }
  }
]