[
  {
    "obj_attr": "None",
    "obj_id": "1",
    "obj_type": "Car",
    "psr": {
      "position": {
        "x": -11.588336178923807,
        "y": -26.6650706176758,
        "z": -3.867017264281657
      },
      "rotation": {
        "x": 0.0016010493780304186,
        "y": -0.06106556493087855,
        "z": -3.1153638151105305
      },
      "scale": {
        "x": 4.280766966128895,
        "y": 0.4208363410151913,
        "z": 1.3137091550134148
      }
    }
  },
  {
    "obj_attr": "None",
    "obj_id": "2",
    "obj_type": "Car",
    "psr": {
      "position": {
        "x": -17.612052923643525,
        "y": -24.483988981645137,
        "z": -4.313086476219533
      },
      "rotation": {
        "x": -0.005288232612908127,
        "y": -0.044106371338842855,
        "z": -3.0720865349651456
      },
      "scale": {
        "x": 4.679800871658749,
        "y": 1.5028988848680007,
        "z": 1.179497439537335
      }
    }
  },
  {
    "obj_attr": "None",
    "obj_id": "4",
    "obj_type": "SUV",
    "psr": {
      "position": {
        "x": 4.234048984531183,
        "y": -8.02035267287135,
        "z": -3.7645000219345093
      },
      "rotation": {
        "x": 0,
        "y": 0,
        "z": 2.0158552860534504
      },
      "scale": {
        "x": 1.8455132087662125,
        "y": 1.850863148094288,
        "z": 0.8389999866485596
      }
    }
  },
  {
    "obj_attr": "None",
    "obj_id": "5",
    "obj_type": "SUV",
    "psr": {
      "position": {
        "x": 8.722156910046868,
        "y": -11.546283096606006,
        "z": -4.058442811307461
      },
      "rotation": {
        "x": -0.02645868511653905,
        "y": -0.06684566492426575,
        "z": 3.0004717905040255
      },
      "scale": {
        "x": 4.181443597111928,
        "y": 1.6509734575666422,
        "z": 1.4178563521591712
      }
    }
  },
  {
    "obj_attr": "None",
    "obj_id": "6",
    "obj_type": "Car",
    "psr": {
      "position": {
        "x": -11.071692092448602,
        "y": -17.616208552739778,
        "z": -4.140165134611981
      },
      "rotation": {
        "x": -0.04407739157795843,
        "y": -0.016205656153536002,
        "z": 3.105718192765709
      },
      "scale": {
        "x": 4.364728456338073,
        "y": 1.4802619223576232,
        "z": 1.3003637900961826
      }
    }
  },
  {
    "obj_attr": "None",
    "obj_id": "8",
    "obj_type": "SUV",
    "psr": {
      "position": {
        "x": 20.583014285411608,
        "y": -14.52727484834272,
        "z": -3.830089883193579
      },
      "rotation": {
        "x": 0.08814029880633314,
        "y": -0.032535910817905495,
        "z": -3.124529574254191
      },
      "scale": {
        "x": 4.651140191206057,
        "y": 1.7397038912628733,
        "z": 1.1153119993171796
      }
    }
  }
]