[
  {
    "obj_attr": "None",
    "obj_id": "1",
    "obj_type": "SUV",
    "psr": {
      "position": {
        "x": -19.055619829247416,
        "y": -17.61670967234112,
        "z": -4.261713052274031
      },
      "rotation": {
        "x": 0.05997104394814402,
        "y": -0.014537892767215656,
        "z": 3.0457689845571045
      },
      "scale": {
        "x": 3.7779865406861757,
        "y": 1.3089115268312896,
        "z": 1.2172970858603915
      }
    }
  },
  {
    "obj_attr": "None",
    "obj_id": "2",
    "obj_type": "Small_Truck",
    "psr": {
      "position": {
        "x": -14.22728212325402,
        "y": -14.28324091993499,
        "z": -3.727913772632295
      },
      "rotation": {
        "x": -0.000254721243090167,
        "y": 0.03242276032090992,
        "z": 3.1317330089281397
      },
      "scale": {
        "x": 5.072798117436955,
        "y": 2.0896235996518895,
        "z": 2.075397183944002
      }
    }
  },
  {
    "obj_attr": "None",
    "obj_id": "3",
    "obj_type": "SUV",
    "psr": {
      "position": {
        "x": -8.13570533538857,
        "y": -26.53303259713873,
        "z": -3.53570208242024
      },
      "rotation": {
        "x": -0.030062035817402553,
        "y": -0.03915940286819055,
        "z": -3.0109769940343125
      },
      "scale": {
        "x": 3.997006544370547,
        "y": 1.4671381317401775,
        "z": 1.5672572600623615
      }
    }
  },
  {
    "obj_attr": "None",
    "obj_id": "4",
    "obj_type": "Car",
    "psr": {
      "position": {
        "x": -17.507614096190398,
        "y": -32.25910751674616,
        "z": -4.259060415750985
      },
      "rotation": {
        "x": -0.021773433742045795,
        "y": -0.08448683559067052,
        "z": -2.751642804509091
      },
      "scale": {
        "x": 4.454151805191872,
        "y": 1.5791453736737575,
        "z": 1.1123813620913576
      }
    }
  },
  {
    "obj_attr": "None",
    "obj_id": "5",
    "obj_type": "Car",
    "psr": {
      "position": {
        "x": 32.65456276354196,
        "y": -12.944137130670452,
        "z": -3.477598081829208
      },
      "rotation": {
        "x": 0.2035291254736863,
        "y": -0.02941612295129875,
        "z": -2.9731578980147977
      },
      "scale": {
        "x": 3.9653768172224937,
        "y": 1.399800557039023,
        "z": 0.7052017107089098
      }
    }
  },
  {
    "obj_attr": "None",
    "obj_id": "6",
    "obj_type": "SUV",
    "psr": {
      "position": {
        "x": 15.383696971870712,
        "y": -14.126186424008708,
        "z": -3.8838249592339524
      },
      "rotation": {
        "x": 0.02562446823749165,
        "y": -0.03816191343476203,
        "z": -3.12400247527064
      },
      "scale": {
        "x": 4.776510681204121,
        "y": 1.7633107298590822,
        "z": 1.2866338728530327
      }
    }
  },
  {
    "obj_attr": "None",
    "obj_id": "7",
    "obj_type": "SUV",
    "psr": {
      "position": {
        "x": 23.951690569581103,
        "y": -20.00885065225911,
        "z": -4.295228097401361
      },
      "rotation": {
        "x": 0.024726673636790958,
        "y": 0.019447064685536107,
        "z": -3.06260799856179
      },
      "scale": {
        "x": 3.926977996347181,
        "y": 1.5513309923479561,
        "z": 1.0907010563686517
      }
    }
  }
]