[
  {
    "obj_attr": "None",
    "obj_id": "1",
    "obj_type": "Car",
    "psr": {
      "position": {
        "x": -17.613176731544453,
        "y": -24.555844262299825,
        "z": -4.332944252161394
      },
      "rotation": {
        "x": -0.03943577532508191,
        "y": -0.05560008219657467,
        "z": -3.0281462522101616
      },
      "scale": {
        "x": 4.677634706803272,
        "y": 1.5329947341228136,
        "z": 1.1720608797037222
      }
    }
  },
  {
    "obj_attr": "None",
    "obj_id": "2",
    "obj_type": "Small_Car",
    "psr": {
      "position": {
        "x": -11.579770740037825,
        "y": -26.816444779653768,
        "z": -3.7242655017050246
      },
      "rotation": {
        "x": -0.0006199028013639991,
        "y": -0.061083382281613245,
        "z": -3.045599544730105
      },
      "scale": {
        "x": 4.12750058773936,
        "y": 0.6540543086597779,
        "z": 1.0113943329467567
      }
    }
  },
  {
    "obj_attr": "None",
    "obj_id": "5",
    "obj_type": "Car",
    "psr": {
      "position": {
        "x": -17.23357611643164,
        "y": -39.79603872897728,
        "z": -4.148894893872322
      },
      "rotation": {
        "x": -0.015596214978210433,
        "y": -0.08630619197146662,
        "z": -0.07959428902306111
      },
      "scale": {
        "x": 4.462365668470119,
        "y": 0.24241683111828674,
        "z": 0.7238201593717717
      }
    }
  }
]