[
  {
    "obj_attr": "None",
    "obj_id": "1",
    "obj_type": "Car",
    "psr": {
      "position": {
        "x": -11.518867316931901,
        "y": -26.763784308051463,
        "z": -4.022867012204468
      },
      "rotation": {
        "x": -0.05015235106330732,
        "y": -0.0629012594702344,
        "z": -3.107806939338896
      },
      "scale": {
        "x": 4.208400387722438,
        "y": 0.6173055550919083,
        "z": 0.9698384886503325
      }
    }
  },
  {
    "obj_attr": "None",
    "obj_id": "2",
    "obj_type": "Car",
    "psr": {
      "position": {
        "x": -17.599410377618522,
        "y": -24.50229004913546,
        "z": -4.316644256847949
      },
      "rotation": {
        "x": -0.013991323569682163,
        "y": -0.044862647754776996,
        "z": -3.0637475807881884
      },
      "scale": {
        "x": 4.803105337522086,
        "y": 1.5090679723235025,
        "z": 1.1733914844638318
      }
    }
  },
  {
    "obj_attr": "None",
    "obj_id": "5",
    "obj_type": "SUV",
    "psr": {
      "position": {
        "x": 4.485654617641987,
        "y": -8.828898287530325,
        "z": -4.295405276832939
      },
      "rotation": {
        "x": 0.02107851521756536,
        "y": -0.09718747183890984,
        "z": 2.436487119145133
      },
      "scale": {
        "x": 3.3679189765188995,
        "y": 1.595122587921466,
        "z": 1.6008236831893878
      }
    }
  },
  {
    "obj_attr": "None",
    "obj_id": "9",
    "obj_type": "Car",
    "psr": {
      "position": {
        "x": -4.101138561766958,
        "y": -26.106442439901272,
        "z": -3.3245665354226626
      },
      "rotation": {
        "x": -0.05716565704738268,
        "y": -0.03385412148049775,
        "z": -3.02096018263842
      },
      "scale": {
        "x": 4.717346517312891,
        "y": 1.6183325611478603,
        "z": 1.7010670855744645
      }
    }
  },
  {
    "obj_attr": "None",
    "obj_id": "11",
    "obj_type": "Adult",
    "psr": {
      "position": {
        "x": 8.806097108668384,
        "y": -6.583055798550956,
        "z": -2.7205682839031455
      },
      "rotation": {
        "x": 0,
        "y": 0,
        "z": -3.086943214009874
      },
      "scale": {
        "x": 0.17333967084852073,
        "y": 0.2078258681588816,
        "z": 0.18577692202515958
      }
    }
  }
]