[
  {
    "obj_attr": "None",
    "obj_id": "1",
    "obj_type": "Car",
    "psr": {
      "position": {
        "x": -24.747471850468788,
        "y": -24.837991994469927,
        "z": -4.822540517786722
      },
      "rotation": {
        "x": 0.007776005807938725,
        "y": -0.06059019011754342,
        "z": -3.0138728356182916
      },
      "scale": {
        "x": 2.4022385537181385,
        "y": 0.4601182053947461,
        "z": 0.5333104163460033
      }
    }
  },
  {
    "obj_attr": "None",
    "obj_id": "2",
    "obj_type": "Small_Truck",
    "psr": {
      "position": {
        "x": -1.181749212385594,
        "y": -22.913857712483,
        "z": -3.0506589920727047
      },
      "rotation": {
        "x": -0.05077242400697265,
        "y": -0.0154765968101016,
        "z": -3.010680257307171
      },
      "scale": {
        "x": 4.977288595286824,
        "y": 1.9572971664597347,
        "z": 2.5046609082693436
      }
    }
  },
  {
    "obj_attr": "None",
    "obj_id": "3",
    "obj_type": "Car",
    "psr": {
      "position": {
        "x": 7.9143352247964005,
        "y": -28.25579629073088,
        "z": -3.4514491695883494
      },
      "rotation": {
        "x": -0.04020256308828562,
        "y": 0.02863872034890945,
        "z": -3.0106929596902186
      },
      "scale": {
        "x": 4.744128451554684,
        "y": 1.5744521444003163,
        "z": 1.254238599166544
      }
    }
  },
  {
    "obj_attr": "None",
    "obj_id": "4",
    "obj_type": "Bus",
    "psr": {
      "position": {
        "x": 32.986130802707194,
        "y": -22.967071533002926,
        "z": -4.564249595745244
      },
      "rotation": {
        "x": 0.07095286513523379,
        "y": 0.04177018884344884,
        "z": 3.114840762056062
      },
      "scale": {
        "x": 3.2199013762557027,
        "y": 2.3544159706005434,
        "z": 1.473095588582444
      }
    }
  }
]